pickles/__init__.py
pickles/admin.py
pickles/apps.py
pickles/forms.py
pickles/models.py
pickles/tests.py
pickles/views.py
pickles/api/__init__.py
pickles/api/urls.py
pickles/api/views.py
pickles/migrations/0001_initial.py
pickles/migrations/0002_alter_pickle_id.py
pickles/migrations/0003_delete_pickle.py
pickles/migrations/0004_pickle.py
pickles/migrations/__init__.py
django_pickled_model-1.1.3.dist-info/LICENSE
django_pickled_model-1.1.3.dist-info/METADATA
django_pickled_model-1.1.3.dist-info/WHEEL
django_pickled_model-1.1.3.dist-info/top_level.txt
django_pickled_model-1.1.3.dist-info/RECORD
