Metadata-Version: 2.2
Name: django-pickled-model
Version: 1.1.3
Summary: Django pickled model provides you a model with dynamic data types.
Home-page: https://github.com/Amir-4m/django-pickled-model
Author: Amir Amiri
Author-email: amiriamirr533@gmail.com
License: MIT License
Project-URL: Bug Tracker, https://github.com/Amir-4m/django-pickled-model/issues
Classifier: Environment :: Web Environment
Classifier: Framework :: Django
Classifier: Framework :: Django :: 3.2
Classifier: Framework :: Django :: 4.2
Classifier: Intended Audience :: Developers
Classifier: License :: OSI Approved :: MIT License
Classifier: Operating System :: OS Independent
Classifier: Programming Language :: Python
Classifier: Programming Language :: Python :: 3
Classifier: Programming Language :: Python :: 3 :: Only
Classifier: Programming Language :: Python :: 3.7
Classifier: Programming Language :: Python :: 3.8
Classifier: Programming Language :: Python :: 3.9
Classifier: Programming Language :: Python :: 3.10
Classifier: Topic :: Internet :: WWW/HTTP
Classifier: Topic :: Internet :: WWW/HTTP :: Dynamic Content
Requires-Python: >=3.7
License-File: LICENSE
Requires-Dist: Django<4.3,>=3.2
Requires-Dist: djangorestframework
Requires-Dist: django-picklefield
